Metadata-Version: 2.1
Name: yonk
Version: 0.1.1
Summary: yonk is a Python package for creating data science structure
Home-page: https://github.com/DARK-art108/quant
Author: Ritesh Yadav
